autoprognosis/__init__.py
autoprognosis/logger.py
autoprognosis/version.py
autoprognosis/apps/__init__.py
autoprognosis/apps/common/__init__.py
autoprognosis/apps/common/login.py
autoprognosis/apps/common/pandas_to_streamlit.py
autoprognosis/apps/extras/__init__.py
autoprognosis/apps/extras/biobank_cvd.py
autoprognosis/apps/extras/biobank_diabetes.py
autoprognosis/deploy/__init__.py
autoprognosis/deploy/build.py
autoprognosis/deploy/proto.py
autoprognosis/deploy/run.py
autoprognosis/deploy/utils.py
autoprognosis/exceptions/__init__.py
autoprognosis/explorers/__init__.py
autoprognosis/explorers/classifiers.py
autoprognosis/explorers/classifiers_combos.py
autoprognosis/explorers/regression.py
autoprognosis/explorers/regression_combos.py
autoprognosis/explorers/risk_estimation.py
autoprognosis/explorers/risk_estimation_combos.py
autoprognosis/explorers/core/__init__.py
autoprognosis/explorers/core/defaults.py
autoprognosis/explorers/core/optimizer.py
autoprognosis/explorers/core/selector.py
autoprognosis/explorers/core/optimizers/__init__.py
autoprognosis/explorers/core/optimizers/bayesian.py
autoprognosis/explorers/core/optimizers/hyperband.py
autoprognosis/hooks/__init__.py
autoprognosis/hooks/base.py
autoprognosis/hooks/default.py
autoprognosis/plugins/__init__.py
autoprognosis/plugins/core/__init__.py
autoprognosis/plugins/core/base_plugin.py
autoprognosis/plugins/core/params.py
autoprognosis/plugins/ensemble/__init__.py
autoprognosis/plugins/ensemble/classifiers.py
autoprognosis/plugins/ensemble/combos.py
autoprognosis/plugins/ensemble/regression.py
autoprognosis/plugins/ensemble/risk_estimation.py
autoprognosis/plugins/explainers/__init__.py
autoprognosis/plugins/explainers/base.py
autoprognosis/plugins/explainers/plugin_invase.py
autoprognosis/plugins/explainers/plugin_kernel_shap.py
autoprognosis/plugins/explainers/plugin_lime.py
autoprognosis/plugins/explainers/plugin_risk_effect_size.py
autoprognosis/plugins/explainers/plugin_shap_permutation_sampler.py
jori_autoprognosis-0.2.5.dist-info/LICENSE
jori_autoprognosis-0.2.5.dist-info/METADATA
jori_autoprognosis-0.2.5.dist-info/WHEEL
jori_autoprognosis-0.2.5.dist-info/top_level.txt
jori_autoprognosis-0.2.5.dist-info/RECORD
