Metadata-Version: 2.1
Name: jori-autoprognosis
Version: 0.2.5
Summary: Test
Home-page: https://github.com/Jori-Health/autoprognosis
Author: Bryan Kyritz
Author-email: bryan@jori.health
License: Apache-2.0 license
Platform: any
Classifier: Programming Language :: Python :: 3
Classifier: Topic :: Scientific/Engineering :: Artificial Intelligence
Classifier: Intended Audience :: Healthcare Industry
Classifier: License :: OSI Approved :: BSD License
Classifier: Operating System :: OS Independent
License-File: LICENSE
Requires-Dist: torch >=1.10
Requires-Dist: numpy >=1.20
Requires-Dist: pandas <2.0,>=1.3
Requires-Dist: scikit-learn >=1.0
Requires-Dist: scipy >=1.3.2
Requires-Dist: shap >=0.40.0
Requires-Dist: optuna ==3.1.0
Requires-Dist: hyperimpute >=0.1.16
Requires-Dist: statsmodels
Requires-Dist: pyod
Requires-Dist: pydantic
Requires-Dist: seaborn
Requires-Dist: matplotlib
Requires-Dist: cloudpickle
Requires-Dist: lifelines
Requires-Dist: loguru
Requires-Dist: redis
Requires-Dist: joblib
Requires-Dist: importlib-metadata ; python_version < "3.8"
Provides-Extra: testing
Requires-Dist: setuptools ; extra == 'testing'
Requires-Dist: bandit ; extra == 'testing'
Requires-Dist: black ; extra == 'testing'
Requires-Dist: black-nb ; extra == 'testing'
Requires-Dist: darglint ; extra == 'testing'
Requires-Dist: doc8 ; extra == 'testing'
Requires-Dist: flake8 ; extra == 'testing'
Requires-Dist: isort ; extra == 'testing'
Requires-Dist: nbconvert ; extra == 'testing'
Requires-Dist: nbformat ; extra == 'testing'
Requires-Dist: pytest ; extra == 'testing'
Requires-Dist: pytest-benchmark ; extra == 'testing'
Requires-Dist: pytest-cov ; extra == 'testing'
Requires-Dist: pytest-xdist[psutil] ; extra == 'testing'
Requires-Dist: pytest-xprocess ; extra == 'testing'
Requires-Dist: py ; extra == 'testing'
Requires-Dist: pre-commit ; extra == 'testing'
Requires-Dist: tabulate ; extra == 'testing'
Requires-Dist: click ; extra == 'testing'
Requires-Dist: optuna ; extra == 'testing'
Requires-Dist: pycox ; extra == 'testing'
